main.py
dgt-0.0.1.dist-info/METADATA
dgt-0.0.1.dist-info/WHEEL
dgt-0.0.1.dist-info/top_level.txt
dgt-0.0.1.dist-info/RECORD
