Metadata-Version: 2.1
Name: dgt
Version: 0.0.1
Summary: dgt
Author: 4sushi
License: MIT
Keywords: dgt
Platform: UNKNOWN
Classifier: Programming Language :: Python :: 3
Classifier: License :: OSI Approved :: MIT License
Classifier: Operating System :: OS Independent
Requires-Python: >=3.7
